ing0.py
ingzero-0.1.1.dist-info/LICENSE
ingzero-0.1.1.dist-info/METADATA
ingzero-0.1.1.dist-info/WHEEL
ingzero-0.1.1.dist-info/top_level.txt
ingzero-0.1.1.dist-info/RECORD
