Metadata-Version: 2.1
Name: ingzero
Version: 0.1.1
Summary: Divers productivity tools
Requires-Python: >=3.10
License-File: LICENSE
Requires-Dist: certifi ==2023.11.17
Requires-Dist: charset-normalizer ==3.3.2
Requires-Dist: eralchemy2 ==1.3.8
Requires-Dist: greenlet ==3.0.1
Requires-Dist: idna ==3.4
Requires-Dist: lxml ==4.9.3
Requires-Dist: pygraphviz ==1.11
Requires-Dist: requests ==2.31.0
Requires-Dist: sqlalchemy ==2.0.23
Requires-Dist: typing-extensions ==4.8.0
Requires-Dist: urllib3 ==2.1.0
